{
 "custom_fields": [
  {
   "_assign": null,
   "_comments": null,
   "_liked_by": null,
   "_user_tags": null,
   "allow_in_quick_entry": 0,
   "allow_on_submit": 0,
   "bold": 0,
   "collapsible": 0,
   "collapsible_depends_on": null,
   "columns": 0,
   "creation": "2023-09-20 10:29:49.340323",
   "default": null,
   "depends_on": null,
   "description": null,
   "docstatus": 0,
   "dt": "Supplier",
   "fetch_from": null,
   "fetch_if_empty": 0,
   "fieldname": "pan",
   "fieldtype": "Data",
   "hidden": 0,
   "hide_border": 0,
   "hide_days": 0,
   "hide_seconds": 0,
   "idx": 0,
   "ignore_user_permissions": 0,
   "ignore_xss_filter": 0,
   "in_global_search": 0,
   "in_list_view": 0,
   "in_preview": 0,
   "in_standard_filter": 0,
   "insert_after": "gstin",
   "is_system_generated": 1,
   "is_virtual": 0,
   "label": "PAN",
   "length": 0,
   "mandatory_depends_on": null,
   "modified": "2023-09-20 10:29:49.340323",
   "modified_by": "Administrator",
   "module": null,
   "name": "Supplier-pan",
   "no_copy": 0,
   "non_negative": 0,
   "options": null,
   "owner": "Administrator",
   "permlevel": 0,
   "precision": "",
   "print_hide": 0,
   "print_hide_if_no_value": 0,
   "print_width": null,
   "read_only": 0,
   "read_only_depends_on": "eval: doc.gstin",
   "report_hide": 0,
   "reqd": 0,
   "search_index": 0,
   "sort_options": 0,
   "translatable": 0,
   "unique": 0,
   "width": null
  },
  {
   "_assign": null,
   "_comments": null,
   "_liked_by": null,
   "_user_tags": null,
   "allow_in_quick_entry": 0,
   "allow_on_submit": 0,
   "bold": 0,
   "collapsible": 0,
   "collapsible_depends_on": null,
   "columns": 0,
   "creation": "2023-09-20 10:29:49.852257",
   "default": null,
   "depends_on": null,
   "description": null,
   "docstatus": 0,
   "dt": "Supplier",
   "fetch_from": null,
   "fetch_if_empty": 0,
   "fieldname": "tax_details_section",
   "fieldtype": "Section Break",
   "hidden": 0,
   "hide_border": 0,
   "hide_days": 0,
   "hide_seconds": 0,
   "idx": 0,
   "ignore_user_permissions": 0,
   "ignore_xss_filter": 0,
   "in_global_search": 0,
   "in_list_view": 0,
   "in_preview": 0,
   "in_standard_filter": 0,
   "insert_after": "tax_withholding_category",
   "is_system_generated": 1,
   "is_virtual": 0,
   "label": "Tax Details",
   "length": 0,
   "mandatory_depends_on": null,
   "modified": "2023-09-20 10:29:49.852257",
   "modified_by": "Administrator",
   "module": null,
   "name": "Supplier-tax_details_section",
   "no_copy": 0,
   "non_negative": 0,
   "options": null,
   "owner": "Administrator",
   "permlevel": 0,
   "precision": "",
   "print_hide": 0,
   "print_hide_if_no_value": 0,
   "print_width": null,
   "read_only": 0,
   "read_only_depends_on": null,
   "report_hide": 0,
   "reqd": 0,
   "search_index": 0,
   "sort_options": 0,
   "translatable": 1,
   "unique": 0,
   "width": null
  },
  {
   "_assign": null,
   "_comments": null,
   "_liked_by": null,
   "_user_tags": null,
   "allow_in_quick_entry": 0,
   "allow_on_submit": 0,
   "bold": 0,
   "collapsible": 0,
   "collapsible_depends_on": null,
   "columns": 0,
   "creation": "2023-09-20 10:29:49.855105",
   "default": null,
   "depends_on": null,
   "description": null,
   "docstatus": 0,
   "dt": "Supplier",
   "fetch_from": null,
   "fetch_if_empty": 0,
   "fieldname": "gstin",
   "fieldtype": "Autocomplete",
   "hidden": 0,
   "hide_border": 0,
   "hide_days": 0,
   "hide_seconds": 0,
   "idx": 0,
   "ignore_user_permissions": 0,
   "ignore_xss_filter": 0,
   "in_global_search": 0,
   "in_list_view": 0,
   "in_preview": 0,
   "in_standard_filter": 0,
   "insert_after": "tax_details_section",
   "is_system_generated": 1,
   "is_virtual": 0,
   "label": "GSTIN / UIN",
   "length": 0,
   "mandatory_depends_on": null,
   "modified": "2023-09-20 10:29:49.855105",
   "modified_by": "Administrator",
   "module": null,
   "name": "Supplier-gstin",
   "no_copy": 0,
   "non_negative": 0,
   "options": null,
   "owner": "Administrator",
   "permlevel": 0,
   "precision": "",
   "print_hide": 0,
   "print_hide_if_no_value": 0,
   "print_width": null,
   "read_only": 0,
   "read_only_depends_on": null,
   "report_hide": 0,
   "reqd": 0,
   "search_index": 0,
   "sort_options": 0,
   "translatable": 0,
   "unique": 0,
   "width": null
  },
  {
   "_assign": null,
   "_comments": null,
   "_liked_by": null,
   "_user_tags": null,
   "allow_in_quick_entry": 0,
   "allow_on_submit": 0,
   "bold": 0,
   "collapsible": 0,
   "collapsible_depends_on": null,
   "columns": 0,
   "creation": "2023-09-20 10:29:49.858006",
   "default": null,
   "depends_on": null,
   "description": null,
   "docstatus": 0,
   "dt": "Supplier",
   "fetch_from": null,
   "fetch_if_empty": 0,
   "fieldname": "tax_details_column_break",
   "fieldtype": "Column Break",
   "hidden": 0,
   "hide_border": 0,
   "hide_days": 0,
   "hide_seconds": 0,
   "idx": 0,
   "ignore_user_permissions": 0,
   "ignore_xss_filter": 0,
   "in_global_search": 0,
   "in_list_view": 0,
   "in_preview": 0,
   "in_standard_filter": 0,
   "insert_after": "pan",
   "is_system_generated": 1,
   "is_virtual": 0,
   "label": null,
   "length": 0,
   "mandatory_depends_on": null,
   "modified": "2023-09-20 10:29:49.858006",
   "modified_by": "Administrator",
   "module": null,
   "name": "Supplier-tax_details_column_break",
   "no_copy": 0,
   "non_negative": 0,
   "options": null,
   "owner": "Administrator",
   "permlevel": 0,
   "precision": "",
   "print_hide": 0,
   "print_hide_if_no_value": 0,
   "print_width": null,
   "read_only": 0,
   "read_only_depends_on": null,
   "report_hide": 0,
   "reqd": 0,
   "search_index": 0,
   "sort_options": 0,
   "translatable": 1,
   "unique": 0,
   "width": null
  },
  {
   "_assign": null,
   "_comments": null,
   "_liked_by": null,
   "_user_tags": null,
   "allow_in_quick_entry": 0,
   "allow_on_submit": 0,
   "bold": 0,
   "collapsible": 0,
   "collapsible_depends_on": null,
   "columns": 0,
   "creation": "2023-09-20 10:29:49.860790",
   "default": "Unregistered",
   "depends_on": null,
   "description": null,
   "docstatus": 0,
   "dt": "Supplier",
   "fetch_from": null,
   "fetch_if_empty": 0,
   "fieldname": "gst_category",
   "fieldtype": "Select",
   "hidden": 0,
   "hide_border": 0,
   "hide_days": 0,
   "hide_seconds": 0,
   "idx": 0,
   "ignore_user_permissions": 0,
   "ignore_xss_filter": 0,
   "in_global_search": 0,
   "in_list_view": 0,
   "in_preview": 0,
   "in_standard_filter": 0,
   "insert_after": "tax_details_column_break",
   "is_system_generated": 1,
   "is_virtual": 0,
   "label": "GST Category",
   "length": 0,
   "mandatory_depends_on": null,
   "modified": "2023-09-20 10:29:49.860790",
   "modified_by": "Administrator",
   "module": null,
   "name": "Supplier-gst_category",
   "no_copy": 0,
   "non_negative": 0,
   "options": "Registered Regular\nRegistered Composition\nUnregistered\nSEZ\nOverseas\nDeemed Export\nUIN Holders\nTax Deductor",
   "owner": "Administrator",
   "permlevel": 0,
   "precision": "",
   "print_hide": 0,
   "print_hide_if_no_value": 0,
   "print_width": null,
   "read_only": 0,
   "read_only_depends_on": null,
   "report_hide": 0,
   "reqd": 1,
   "search_index": 0,
   "sort_options": 0,
   "translatable": 0,
   "unique": 0,
   "width": null
  },
  {
   "_assign": null,
   "_comments": null,
   "_liked_by": null,
   "_user_tags": null,
   "allow_in_quick_entry": 0,
   "allow_on_submit": 0,
   "bold": 0,
   "collapsible": 0,
   "collapsible_depends_on": null,
   "columns": 0,
   "creation": "2023-09-20 10:29:50.395637",
   "default": null,
   "depends_on": "eval:doc.is_transporter",
   "description": null,
   "docstatus": 0,
   "dt": "Supplier",
   "fetch_from": null,
   "fetch_if_empty": 0,
   "fieldname": "gst_transporter_id",
   "fieldtype": "Data",
   "hidden": 0,
   "hide_border": 0,
   "hide_days": 0,
   "hide_seconds": 0,
   "idx": 0,
   "ignore_user_permissions": 0,
   "ignore_xss_filter": 0,
   "in_global_search": 0,
   "in_list_view": 0,
   "in_preview": 0,
   "in_standard_filter": 0,
   "insert_after": "gst_category",
   "is_system_generated": 1,
   "is_virtual": 0,
   "label": "GST Transporter ID",
   "length": 0,
   "mandatory_depends_on": null,
   "modified": "2023-09-20 10:29:50.395637",
   "modified_by": "Administrator",
   "module": null,
   "name": "Supplier-gst_transporter_id",
   "no_copy": 0,
   "non_negative": 0,
   "options": null,
   "owner": "Administrator",
   "permlevel": 0,
   "precision": "",
   "print_hide": 0,
   "print_hide_if_no_value": 0,
   "print_width": null,
   "read_only": 0,
   "read_only_depends_on": null,
   "report_hide": 0,
   "reqd": 0,
   "search_index": 0,
   "sort_options": 0,
   "translatable": 0,
   "unique": 0,
   "width": null
  },
  {
   "_assign": null,
   "_comments": null,
   "_liked_by": null,
   "_user_tags": null,
   "allow_in_quick_entry": 0,
   "allow_on_submit": 0,
   "bold": 0,
   "collapsible": 0,
   "collapsible_depends_on": null,
   "columns": 0,
   "creation": "2023-09-20 10:29:50.398588",
   "default": null,
   "depends_on": "eval:in_list([\"Registered Regular\", \"Overseas\", \"Unregistered\"], doc.gst_category)",
   "description": null,
   "docstatus": 0,
   "dt": "Supplier",
   "fetch_from": null,
   "fetch_if_empty": 0,
   "fieldname": "is_reverse_charge_applicable",
   "fieldtype": "Check",
   "hidden": 0,
   "hide_border": 0,
   "hide_days": 0,
   "hide_seconds": 0,
   "idx": 0,
   "ignore_user_permissions": 0,
   "ignore_xss_filter": 0,
   "in_global_search": 0,
   "in_list_view": 0,
   "in_preview": 0,
   "in_standard_filter": 0,
   "insert_after": "gst_transporter_id",
   "is_system_generated": 1,
   "is_virtual": 0,
   "label": "Reverse Charge Applicable",
   "length": 0,
   "mandatory_depends_on": null,
   "modified": "2023-09-20 10:29:50.398588",
   "modified_by": "Administrator",
   "module": null,
   "name": "Supplier-is_reverse_charge_applicable",
   "no_copy": 0,
   "non_negative": 0,
   "options": null,
   "owner": "Administrator",
   "permlevel": 0,
   "precision": "",
   "print_hide": 1,
   "print_hide_if_no_value": 0,
   "print_width": null,
   "read_only": 0,
   "read_only_depends_on": null,
   "report_hide": 0,
   "reqd": 0,
   "search_index": 0,
   "sort_options": 0,
   "translatable": 0,
   "unique": 0,
   "width": null
  },
  {
   "_assign": null,
   "_comments": null,
   "_liked_by": null,
   "_user_tags": null,
   "allow_in_quick_entry": 1,
   "allow_on_submit": 0,
   "bold": 0,
   "collapsible": 0,
   "collapsible_depends_on": null,
   "columns": 0,
   "creation": "2023-10-06 11:44:32.899116",
   "default": null,
   "depends_on": null,
   "description": null,
   "docstatus": 0,
   "dt": "Supplier",
   "fetch_from": null,
   "fetch_if_empty": 0,
   "fieldname": "custom_city",
   "fieldtype": "Data",
   "hidden": 0,
   "hide_border": 0,
   "hide_days": 0,
   "hide_seconds": 0,
   "idx": 5,
   "ignore_user_permissions": 0,
   "ignore_xss_filter": 0,
   "in_global_search": 0,
   "in_list_view": 0,
   "in_preview": 0,
   "in_standard_filter": 0,
   "insert_after": "country",
   "is_system_generated": 0,
   "is_virtual": 0,
   "label": "City",
   "length": 0,
   "mandatory_depends_on": null,
   "modified": "2023-10-06 11:44:32.899116",
   "modified_by": "Administrator",
   "module": null,
   "name": "Supplier-custom_city",
   "no_copy": 0,
   "non_negative": 0,
   "options": null,
   "owner": "Administrator",
   "permlevel": 0,
   "precision": "",
   "print_hide": 0,
   "print_hide_if_no_value": 0,
   "print_width": null,
   "read_only": 0,
   "read_only_depends_on": null,
   "report_hide": 0,
   "reqd": 0,
   "search_index": 0,
   "sort_options": 0,
   "translatable": 1,
   "unique": 0,
   "width": null
  },
  {
   "_assign": null,
   "_comments": null,
   "_liked_by": null,
   "_user_tags": null,
   "allow_in_quick_entry": 0,
   "allow_on_submit": 0,
   "bold": 0,
   "collapsible": 0,
   "collapsible_depends_on": null,
   "columns": 0,
   "creation": "2023-10-06 12:35:16.136138",
   "default": null,
   "depends_on": null,
   "description": null,
   "docstatus": 0,
   "dt": "Supplier",
   "fetch_from": null,
   "fetch_if_empty": 0,
   "fieldname": "custom_series",
   "fieldtype": "Data",
   "hidden": 0,
   "hide_border": 0,
   "hide_days": 0,
   "hide_seconds": 0,
   "idx": 2,
   "ignore_user_permissions": 0,
   "ignore_xss_filter": 0,
   "in_global_search": 0,
   "in_list_view": 0,
   "in_preview": 0,
   "in_standard_filter": 0,
   "insert_after": "naming_series",
   "is_system_generated": 0,
   "is_virtual": 0,
   "label": "Series",
   "length": 0,
   "mandatory_depends_on": null,
   "modified": "2023-10-06 12:35:16.136138",
   "modified_by": "Administrator",
   "module": null,
   "name": "Supplier-custom_series",
   "no_copy": 0,
   "non_negative": 0,
   "options": null,
   "owner": "Administrator",
   "permlevel": 0,
   "precision": "",
   "print_hide": 0,
   "print_hide_if_no_value": 0,
   "print_width": null,
   "read_only": 0,
   "read_only_depends_on": null,
   "report_hide": 0,
   "reqd": 0,
   "search_index": 0,
   "sort_options": 0,
   "translatable": 1,
   "unique": 0,
   "width": null
  }
 ],
 "custom_perms": [],
 "doctype": "Supplier",
 "links": [
  {
   "creation": "2013-01-10 16:34:11",
   "custom": 0,
   "docstatus": 0,
   "group": "Allowed Items",
   "hidden": 0,
   "idx": 1,
   "is_child_table": 0,
   "link_doctype": "Party Specific Item",
   "link_fieldname": "party",
   "modified": "2023-09-20 10:26:30.445503",
   "modified_by": "Administrator",
   "name": "1a007b3eb2",
   "owner": "Administrator",
   "parent": "Supplier",
   "parent_doctype": null,
   "parentfield": "links",
   "parenttype": "DocType",
   "table_fieldname": null
  }
 ],
 "property_setters": [
  {
   "_assign": null,
   "_comments": null,
   "_liked_by": null,
   "_user_tags": null,
   "creation": "2024-01-12 17:06:37.712818",
   "default_value": null,
   "doc_type": "Supplier",
   "docstatus": 0,
   "doctype_or_field": "DocField",
   "field_name": "naming_series",
   "idx": 0,
   "is_system_generated": 0,
   "modified": "2024-01-12 17:06:37.712818",
   "modified_by": "Administrator",
   "module": null,
   "name": "Supplier-naming_series-default",
   "owner": "Administrator",
   "property": "default",
   "property_type": "Text",
   "row_name": null,
   "value": "SUP-.YYYY.-"
  },
  {
   "_assign": null,
   "_comments": null,
   "_liked_by": null,
   "_user_tags": null,
   "creation": "2024-01-12 17:06:37.651204",
   "default_value": null,
   "doc_type": "Supplier",
   "docstatus": 0,
   "doctype_or_field": "DocField",
   "field_name": "naming_series",
   "idx": 0,
   "is_system_generated": 0,
   "modified": "2024-01-12 17:06:37.651204",
   "modified_by": "Administrator",
   "module": null,
   "name": "Supplier-naming_series-options",
   "owner": "Administrator",
   "property": "options",
   "property_type": "Text",
   "row_name": null,
   "value": "SUP-.YYYY.-\nOS.#####\nLL.#####\nCF.#####\nPM.#####\nTR.#####"
  },
  {
   "_assign": null,
   "_comments": null,
   "_liked_by": null,
   "_user_tags": null,
   "creation": "2023-10-13 15:31:24.679636",
   "default_value": null,
   "doc_type": "Supplier",
   "docstatus": 0,
   "doctype_or_field": "DocType",
   "field_name": null,
   "idx": 0,
   "is_system_generated": 0,
   "modified": "2023-10-13 15:31:24.679636",
   "modified_by": "Administrator",
   "module": null,
   "name": "Supplier-main-field_order",
   "owner": "Administrator",
   "property": "field_order",
   "property_type": "Data",
   "row_name": null,
   "value": "[\"naming_series\", \"custom_series\", \"supplier_name\", \"country\", \"custom_city\", \"column_break0\", \"supplier_group\", \"supplier_type\", \"is_transporter\", \"image\", \"defaults_section\", \"default_currency\", \"default_bank_account\", \"column_break_10\", \"default_price_list\", \"payment_terms\", \"internal_supplier_section\", \"is_internal_supplier\", \"represents_company\", \"column_break_16\", \"companies\", \"column_break2\", \"supplier_details\", \"column_break_30\", \"website\", \"language\", \"dashboard_tab\", \"tax_tab\", \"tax_id\", \"column_break_27\", \"tax_category\", \"tax_withholding_category\", \"tax_details_section\", \"gstin\", \"pan\", \"tax_details_column_break\", \"gst_category\", \"gst_transporter_id\", \"is_reverse_charge_applicable\", \"contact_and_address_tab\", \"address_contacts\", \"address_html\", \"column_break1\", \"contact_html\", \"primary_address_and_contact_detail_section\", \"supplier_primary_contact\", \"mobile_no\", \"email_id\", \"column_break_44\", \"supplier_primary_address\", \"primary_address\", \"accounting_tab\", \"accounts\", \"settings_tab\", \"allow_purchase_invoice_creation_without_purchase_order\", \"allow_purchase_invoice_creation_without_purchase_receipt\", \"column_break_54\", \"is_frozen\", \"disabled\", \"warn_rfqs\", \"warn_pos\", \"prevent_rfqs\", \"prevent_pos\", \"block_supplier_section\", \"on_hold\", \"hold_type\", \"column_break_59\", \"release_date\"]"
  },
  {
   "_assign": null,
   "_comments": null,
   "_liked_by": null,
   "_user_tags": null,
   "creation": "2023-10-06 11:56:20.093719",
   "default_value": null,
   "doc_type": "Supplier",
   "docstatus": 0,
   "doctype_or_field": "DocType",
   "field_name": null,
   "idx": 0,
   "is_system_generated": 0,
   "modified": "2023-10-06 11:56:20.093719",
   "modified_by": "Administrator",
   "module": null,
   "name": "Supplier-main-search_fields",
   "owner": "Administrator",
   "property": "search_fields",
   "property_type": "Data",
   "row_name": null,
   "value": "supplier_name, supplier_group,custom_city"
  },
  {
   "_assign": null,
   "_comments": null,
   "_liked_by": null,
   "_user_tags": null,
   "creation": "2023-09-20 10:31:57.676502",
   "default_value": null,
   "doc_type": "Supplier",
   "docstatus": 0,
   "doctype_or_field": "DocField",
   "field_name": "naming_series",
   "idx": 0,
   "is_system_generated": 0,
   "modified": "2023-09-20 10:31:57.676502",
   "modified_by": "Administrator",
   "module": null,
   "name": "Supplier-naming_series-reqd",
   "owner": "Administrator",
   "property": "reqd",
   "property_type": "Check",
   "row_name": null,
   "value": "0"
  }
 ],
 "sync_on_migrate": 1
}